{
	"schemaVersion": 1,
	"id": "hillside",
	"version": "${version}",
	"name": "Hillside Mod",
	"description": "This is my mod!",
	"authors": [
		"Dave"
	],
	"contact": {
		"homepage": "https://fabricmc.net/",
		"sources": "https://github.com/FabricMC/fabric-example-mod"
	},
	"license": "MIT",
	"icon": "",
	"environment": "*",
	"entrypoints": {
		"main": [
			"net.hillsidemod.hillside.Hillside"
		],
		"client": [
			"net.hillsidemod.hillside.HillsideModClient"
		],
		"fabric-datagen": [
          "net.hillsidemod.hillside.HillsideDataGenerator"
		]
	},
	"mixins": [
		"hillside.mixins.json"
	],
	"depends": {
		"fabricloader": ">=0.14.19",
		"minecraft": "~1.20.1",
		"java": ">=17",
		"fabric-api": "*"
	},
	"suggests": {
		"another-mod": "*"
	}
}